{"paymentInformation":{"infoUrl":"https://mining.bit.tube","paymentThreshold":{"min":25,"max":314},"paymentScheme":"PROP","fee":{"feeType":"Fixed","min":0,"max":314},"paymentInterval":900},"locations":["DE"],"isAlive":true,"lastUpdated":"2019-08-10T12:02:31.623Z","url":"https://mining.bit.tube","slug":"1567","coin":{"name":"BitTube","abbreviation":"TUBE","slug":"bittube","algorithm":{"name":"CryptoNight Saber","slug":"cryptonight-saber"}},"poolProfile":{"numberOfSubPools":1,"name":"Mining.bit.tube","slug":"mining-bit-tube"},"servers":[],"mergedCoins":[]}