{"paymentInformation":{"infoUrl":"","paymentThreshold":{"min":314,"max":314},"paymentScheme":null,"fee":{"feeType":"Fixed","min":314,"max":314},"paymentInterval":null},"locations":["US"],"isAlive":false,"lastUpdated":"2019-08-08T16:13:33.924Z","url":"https://deltapool.net","slug":"22","coin":{"name":"Bitcoin","abbreviation":"BTC","slug":"bitcoin","algorithm":{"name":"SHA 256","slug":"sha-256"}},"poolProfile":{"name":"DeltaPool (Private)","slug":"deltapool-private"},"servers":[],"mergedCoins":[]}