{"paymentInformation":{"infoUrl":"https://pool.viabtc.com/pricing","paymentThreshold":{"min":0.01,"max":314},"paymentScheme":"PPS+","fee":{"feeType":"Fixed","min":3,"max":314},"paymentInterval":86400},"locations":["US"],"isAlive":true,"lastUpdated":"2019-08-06T18:51:05.197Z","url":"https://pool.viabtc.com/signup/?refer=220676","slug":"231","coin":{"name":"Bitcoin SV","abbreviation":"BSV","slug":"bitcoin-sv","algorithm":{"name":"SHA 256","slug":"sha-256"}},"poolProfile":{"name":"ViaBTC","slug":"viabtc"},"servers":[{"_id":"5d60042b713a3d3ed81ac272","url":"bsv.viabtc.com","city":"California","country":"United States","continent":"North America","abbreviation":"US","latitude":37.5474,"longitude":-122.3306},{"_id":"5d60042b713a3d3ed81ac273","url":"bitcoin.viabtc.com","city":"California","country":"United States","continent":"North America","abbreviation":"US","latitude":37.5474,"longitude":-122.3306}],"mergedCoins":[],"ports":[{"_id":"5d600434713a3d3ed81ac274","port":8888,"difficulty":"-","description":"Port"},{"_id":"5d60043d713a3d3ed81ac275","port":3333,"difficulty":"-","description":"BTC/BCH/BSV One-click switch address"},{"_id":"5d600447713a3d3ed81ac276","port":443,"difficulty":"-","description":"Alternate Port"},{"_id":"5d600451713a3d3ed81ac277","port":25,"difficulty":"-","description":"Alternate Port 2"},{"_id":"5d60045b713a3d3ed81ac278","port":80,"difficulty":"-","description":"Alternate Port 3"}]}