{"paymentInformation":{"paymentThreshold":{"min":10,"max":314},"fee":{"feeType":"Fixed","min":0.2,"max":314},"infoUrl":"","paymentScheme":"PROP"},"locations":["VN"],"isAlive":true,"lastUpdated":"2019-08-06T15:34:51.162Z","url":"https://easyhash.pro/lbit","slug":"2328","coin":{"numberOfSubPools":2,"name":"LithiumBit","abbreviation":"LBIT","slug":"lithiumbit","algorithm":{"name":"CryptoNight","slug":"cryptonight"}},"poolProfile":{"numberOfSubPools":15,"name":"EasyHash.pro","slug":"easyhash-pro"},"servers":[],"mergedCoins":[]}