{"paymentInformation":{"infoUrl":"https://pools.altpools.com","paymentThreshold":{"min":1,"max":314},"paymentScheme":"PPLNS","fee":{"feeType":"Fixed","min":1,"max":314},"paymentInterval":3600},"locations":["US"],"isAlive":true,"lastUpdated":"2019-08-09T10:43:45.148Z","url":"https://pools.altpools.com","slug":"2733","coin":{"numberOfSubPools":16,"name":"ZCore","abbreviation":"ZCR","slug":"zcore","algorithm":{"name":"Lyra2z","slug":"lyra2z"}},"poolProfile":{"numberOfSubPools":2,"name":"Altpools.com","slug":"altpools-com"},"servers":[],"mergedCoins":[]}