{"paymentInformation":{"paymentThreshold":{"min":1,"max":314},"fee":{"feeType":"Fixed","min":1,"max":314},"infoUrl":"","paymentScheme":"PROP"},"locations":["CA"],"isAlive":true,"lastUpdated":"2019-08-06T15:34:51.162Z","url":"https://webchain.wattpool.net","slug":"3329","coin":{"numberOfSubPools":11,"name":"Webchain","abbreviation":"WEB","slug":"webchain","algorithm":{"name":"Lyra2 Webchain","slug":"lyra2-webchain"}},"poolProfile":{"numberOfSubPools":16,"name":"WattPool.net","slug":"wattpool-net"},"servers":[],"mergedCoins":[]}