{"paymentInformation":{"paymentThreshold":{"min":0.001,"max":314},"fee":{"feeType":"Fixed","min":0.25,"max":314},"infoUrl":"","paymentScheme":"PROP","paymentInterval":7200},"locations":["US"],"isAlive":true,"lastUpdated":"2019-08-06T15:34:51.162Z","url":"https://www.nlpool.nl","slug":"4121","coin":{"numberOfSubPools":11,"name":"Mobit Global","abbreviation":"MBGL","slug":"mobit-global","algorithm":{"name":"Skunk","slug":"skunk"}},"poolProfile":{"numberOfSubPools":112,"name":"NLPool","slug":"nlpool"},"servers":[],"mergedCoins":[]}