{"paymentInformation":{"paymentThreshold":{"min":0.001,"max":314},"fee":{"feeType":"Fixed","min":1,"max":314},"infoUrl":"","paymentScheme":"PROP","paymentInterval":7200},"locations":["LT"],"isAlive":true,"lastUpdated":"2019-08-06T15:34:51.162Z","url":"http://doipool.com","slug":"4698","coin":{"name":"ExecuteCoin","abbreviation":"XCQ","slug":"executecoin","algorithm":{"name":"X11","slug":"x11"}},"poolProfile":{"numberOfSubPools":1,"name":"DoiPool.com","slug":"doipool-com"},"servers":[],"mergedCoins":[]}