{"paymentInformation":{"infoUrl":"http://xao.pool-pay.com","paymentThreshold":{"min":5,"max":314},"paymentScheme":"PROP","fee":{"feeType":"Fixed","min":0,"max":314},"paymentInterval":60},"locations":["DE"],"isAlive":true,"lastUpdated":"2019-08-12T10:32:11.399Z","url":"http://xao.pool-pay.com","slug":"4969","coin":{"numberOfSubPools":5,"name":"Alloy","abbreviation":"XAO","slug":"alloy","algorithm":{"name":"CryptoNight Alloy","slug":"cryptonight-alloy"}},"poolProfile":{"numberOfSubPools":17,"name":"Pool-Pay.com","slug":"pool-pay-com"},"servers":[],"mergedCoins":[]}