{"paymentInformation":{"paymentThreshold":{"min":0.0002,"max":314},"fee":{"feeType":"Fixed","min":1.99,"max":314},"infoUrl":"https://prohashing.com","paymentScheme":"PPLNS","paymentInterval":86400},"locations":["US"],"isAlive":true,"lastUpdated":"2019-08-08T14:51:33.725Z","url":"https://prohashing.com","slug":"6220","coin":{"numberOfSubPools":35,"name":"GameCredits","abbreviation":"GAME","slug":"gamecredits","algorithm":{"name":"Scrypt","slug":"scrypt"}},"poolProfile":{"numberOfSubPools":225,"name":"ProHashing","slug":"prohashing"},"servers":[],"mergedCoins":[]}