{"paymentInformation":{"paymentThreshold":{"min":314,"max":314},"fee":{"feeType":"Fixed","min":1,"max":314},"infoUrl":"","paymentScheme":"PPLNT","paymentInterval":1200},"locations":["NL"],"isAlive":true,"lastUpdated":"2019-08-06T15:34:51.162Z","url":"http://kmd.altpool.pro","slug":"932","coin":{"numberOfSubPools":26,"name":"Komodo","abbreviation":"KMD","slug":"komodo","algorithm":{"name":"Equihash","slug":"equihash"}},"poolProfile":{"numberOfSubPools":46,"name":"AltPool.pro","slug":"altpool-pro"},"servers":[],"mergedCoins":[]}