{"paymentInformation":{"paymentThreshold":{"min":0.003,"max":314},"fee":{"feeType":"Fixed","min":1,"max":314},"infoUrl":"","paymentScheme":"PROP","paymentInterval":86400},"locations":["US"],"isAlive":true,"lastUpdated":"2019-08-06T15:34:51.162Z","url":"http://blazepool.com","slug":"984","coin":{"name":"Verge (Myriad-Groestl)","abbreviation":"XVG","slug":"verge-myriad-groestl","algorithm":{"name":"Myriad Groestl","slug":"myriad-groestl"}},"poolProfile":{"name":"BlazePool","slug":"blazepool"},"servers":[],"mergedCoins":[]}