{"id":"buck","description":"BUCK provides near instant settlement with the option for unshielded and shielded transactions. Transaction fees for most transactions are 0.0001 BUCK. With low transaction fees and its limited 1 billion coin maximum supply, BUCK is the perfect transaction platform for now and the future.","links":[{"type":"Website","url":"https://buck.red/"},{"type":"Explorer","url":"https://explorer.buck.red/"},{"type":"Twitter","url":"https://twitter.com/BUCKcoin"},{"type":"Discord","url":"https://discord.gg/G5KrsBz"},{"type":"BitcoinTalk","url":"https://bitcointalk.org/index.php?topic=2828707.0"},{"type":"GitHub","url":"https://github.com/BuckCoin"}],"name":"Buck","abbreviation":"BUCK","algorithm":{"id":"equihash","name":"Equihash"},"pools":[{"name":"1ds.us","url":"https://equipool.1ds.us","serverLocation":["US"],"paymentInformation":{"paymentScheme":"PPLNS","paymentThreshold":0.001,"fee":0.5}},{"name":"AikaPool.com","url":"https://aikapool.com/buck","serverLocation":["FR"],"paymentInformation":{"paymentScheme":"PROP","paymentThreshold":1000,"fee":1}},{"name":"Buckmine.tk","url":"https://buckmine.tk","serverLocation":["US"],"paymentInformation":{"paymentScheme":"","paymentThreshold":314,"fee":5}}],"wallets":[]}