{"id":"geem","description":"Geem is a decentralized, anonymous cryptocurrency project, based on the CryptoNote technology.","links":[{"type":"Website","url":"https://geem.io/"},{"type":"Explorer","url":"http://geemexplorer.com/"},{"type":"Explorer","url":"https://twitter.com/geem_io"},{"type":"Explorer","url":"https://bitcointalk.org/index.php?topic=2659368.0"},{"type":"Explorer","url":"https://github.com/geemcoin"}],"name":"Geem","abbreviation":"GEEM","algorithm":{"id":"cryptonight","name":"CryptoNight"},"pools":[{"name":"GeemExplorer.com","url":"http://pool.geemexplorer.com","serverLocation":["US"],"paymentInformation":{"paymentScheme":"PROP","paymentThreshold":1,"fee":1}},{"name":"CommunityPool.org","url":"https://communitypool.org/geem","serverLocation":["CA"],"paymentInformation":{"paymentScheme":"PROP","paymentThreshold":1,"fee":0.2}},{"name":"NewPool.pw","url":"https://newpool.pw/geem","serverLocation":["FI"],"paymentInformation":{"paymentScheme":"PROP","paymentThreshold":1,"fee":1}}],"wallets":[]}