{"id":"kreds","description":"The Kreds currency will be used by our team to create an ecosystem of world utility, action-based reward, and currency within several media and news websites.","links":[{"name":"Website","platform":"website","url":"https://www.kredsblockchain.com/"},{"name":"Explorer","platform":"explorer","url":"https://www.kredsexplorer.com/"},{"name":"Facebook","platform":"facebook","url":"https://www.facebook.com/267690480434529"},{"name":"Twitter","platform":"twitter","url":"https://twitter.com/kredsblockchain"},{"name":"Reddit","platform":"reddit","url":"https://reddit.com/r/Kreds"},{"name":"Telegram","platform":"telegram","url":"https://t.me/KredsBlockchain"},{"name":"Discord","platform":"discord","url":"https://discordapp.com/invite/PE5xbsr"},{"name":"BitcoinTalk","platform":"bitcointalk","url":"https://bitcointalk.org/index.php?topic=2886837.0"},{"name":"GitHub","platform":"github","url":"https://github.com/KredsBlockchain"}],"name":"Kreds","abbreviation":"KREDS","algorithm":{"id":"lyra2rev2","name":"Lyra2REv2"},"pools":[{"name":"Suprnova.cc","url":"https://kreds.suprnova.cc","serverLocation":["FR"],"paymentInformation":{"paymentThreshold":{"min":0.1,"max":314},"fee":{"feeType":"Fixed","min":1,"max":314},"infoUrl":"","paymentScheme":"PPLNS"}},{"name":"Mining-Dutch.nl","url":"https://www.mining-dutch.nl/pools/kreds.php","serverLocation":["FR"],"paymentInformation":{"paymentThreshold":{"min":314,"max":314},"fee":{"feeType":"Fixed","min":2,"max":314},"infoUrl":"","paymentScheme":"PROP","paymentInterval":900}},{"name":"PowerMining.pw","url":"https://www.powermining.pw","serverLocation":["CA"],"paymentInformation":{"paymentThreshold":{"min":0.01,"max":314},"fee":{"feeType":"Fixed","min":0.8,"max":314},"infoUrl":"","paymentScheme":"PROP","paymentInterval":3600}},{"name":"Erstweal.com","url":"https://erstweal.com","serverLocation":["US"],"paymentInformation":{"paymentThreshold":{"min":0.1,"max":314},"fee":{"feeType":"Fixed","min":0.5,"max":314},"infoUrl":"","paymentScheme":"PROP","paymentInterval":21600}},{"name":"AHashPool","url":"https://www.ahashpool.com","serverLocation":["SG"],"paymentInformation":{"paymentThreshold":{"min":0.003,"max":314},"fee":{"feeType":"Fixed","min":0.5,"max":314},"infoUrl":"","paymentScheme":"PROP","paymentInterval":86400}},{"name":"BlazePool","url":"http://blazepool.com","serverLocation":["US"],"paymentInformation":{"paymentThreshold":{"min":0.003,"max":314},"fee":{"feeType":"Fixed","min":1,"max":314},"infoUrl":"","paymentScheme":"PROP","paymentInterval":86400}},{"name":"BlockMasters.co","url":"http://blockmasters.co","serverLocation":["DE","US"],"paymentInformation":{"paymentThreshold":{"min":0.0025,"max":314},"fee":{"feeType":"Fixed","min":0.25,"max":314},"infoUrl":"","paymentScheme":"PROP","paymentInterval":86400}},{"name":"AltcoinMiners.us","url":"https://altcoinminers.us","serverLocation":["US"],"paymentInformation":{"paymentThreshold":{"min":0.001,"max":314},"fee":{"feeType":"Fixed","min":0.5,"max":314},"infoUrl":"","paymentScheme":"PROP"}},{"name":"SpeedPool.top","url":"https://speedpool.top","serverLocation":["FR"],"paymentInformation":{"paymentThreshold":{"min":0.01,"max":314},"fee":{"feeType":"Fixed","min":0.5,"max":314},"infoUrl":"","paymentScheme":"PROP","paymentInterval":3600}},{"name":"NLPool","url":"https://www.nlpool.nl","serverLocation":["US"],"paymentInformation":{"paymentThreshold":{"min":0.001,"max":314},"fee":{"feeType":"Fixed","min":0.25,"max":314},"infoUrl":"","paymentScheme":"PROP","paymentInterval":7200}},{"name":"ZergPool","url":"http://zergpool.com","serverLocation":["US"],"paymentInformation":{"paymentThreshold":{"min":0.0001,"max":314},"fee":{"feeType":"Fixed","min":0.5,"max":314},"infoUrl":"","paymentScheme":"PROP","paymentInterval":14400}},{"name":"ProHashing","url":"https://prohashing.com","serverLocation":["US"],"paymentInformation":{"paymentThreshold":{"min":1e-8,"max":314},"fee":{"feeType":"Fixed","min":1.99,"max":314},"infoUrl":"https://prohashing.com","paymentScheme":"PPLNS","paymentInterval":86400}},{"name":"ProHashing","url":"https://prohashing.com","serverLocation":["US"],"paymentInformation":{"paymentThreshold":{"min":1e-8,"max":314},"fee":{"feeType":"Fixed","min":3.99,"max":314},"infoUrl":"https://prohashing.com","paymentScheme":"PPS","paymentInterval":86400}},{"name":"ProHashing","url":"https://prohashing.com","serverLocation":["US"],"paymentInformation":{"paymentThreshold":{"min":1e-8,"max":314},"fee":{"feeType":"Fixed","min":1.99,"max":314},"infoUrl":"https://prohashing.com","paymentScheme":"SOLO","paymentInterval":86400}},{"name":"ZPool","url":"https://zpool.ca/algo/lyra2v2","serverLocation":["DE","US","SG","JP"],"paymentInformation":{"paymentThreshold":{"min":0.05,"max":314},"fee":{"feeType":"Fixed","min":1.15,"max":314},"infoUrl":"https://zpool.ca/algo/lyra2v2","paymentScheme":"PROP","paymentInterval":14400}}]}