{"id":"mutex","description":"Mutex (MUTX) is a private, untraceable, fungible cryptocurrency based on the Monero flavor of the Cryptonote protocol. We are the first privacy platform to focus on providing a foundation for the integration of in-app and gaming assets which can be easily traded in the real world without exposing the private information of users or developers.","links":[{"_id":"5d486ed0d65f4b872821c724","platform":"website","name":"Website","url":"https://mutexcurrency.io/"},{"_id":"5d486ed0d65f4b872821c723","platform":"explorer","name":"Explorer","url":"http://explorer.mutexcurrency.io:8081/"},{"_id":"5d486ed0d65f4b872821c722","platform":"facebook","name":"Facebook","url":"https://www.facebook.com/Mutex-2131326810429088"},{"_id":"5d486ed0d65f4b872821c721","platform":"twitter","name":"Twitter","url":"https://twitter.com/MutexCrypto"},{"_id":"5d486ed0d65f4b872821c720","platform":"reddit","name":"Reddit","url":"https://reddit.com/r/MutexProject"},{"_id":"5d486ed0d65f4b872821c71f","platform":"discord","name":"Discord","url":"https://discord.gg/cK2Bang"},{"_id":"5d486ed0d65f4b872821c71e","platform":"telegram","name":"Telegram","url":"https://t.me/joinchat/G-An1k9Wc9pzQYm4KVVphw"},{"_id":"5d486ed0d65f4b872821c71d","platform":"bitcointalk","name":"BitcoinTalk","url":"https://bitcointalk.org/index.php?topic=4027439.0"},{"_id":"5d486ed0d65f4b872821c71c","platform":"github","name":"GitHub","url":"https://github.com/MutexProject"}],"name":"Mutex","abbreviation":"MUTX","algorithm":{"id":"cryptonight-v7","name":"CryptoNight V7"},"pools":[{"name":"Flyhash.cc","url":"https://flyhash.cc/mutex","serverLocation":["DE"],"paymentInformation":{"paymentThreshold":{"min":314,"max":314},"fee":{"feeType":"Fixed","min":314,"max":314},"infoUrl":"","paymentScheme":""}},{"name":"HashParty.io","url":"http://mutex.hashparty.io","serverLocation":["US"],"paymentInformation":{"paymentThreshold":{"min":10,"max":314},"fee":{"feeType":"Fixed","min":0.5,"max":314},"infoUrl":"","paymentScheme":"PROP","paymentInterval":300}},{"name":"MutexCurrency.io","url":"http://mine.mutexcurrency.io","serverLocation":["US"],"paymentInformation":{"paymentThreshold":{"min":100,"max":314},"fee":{"feeType":"Fixed","min":0,"max":314},"infoUrl":"","paymentScheme":"PROP","paymentInterval":300}},{"name":"Almsoft.net","url":"https://mutex.almsoft.net","serverLocation":["RO"],"paymentInformation":{"paymentThreshold":{"min":100,"max":314},"fee":{"feeType":"Fixed","min":1,"max":314},"infoUrl":"","paymentScheme":"PPLNS"}},{"name":"MultiMiner.us","url":"https://mutex.multiminer.us","serverLocation":["US"],"paymentInformation":{"paymentThreshold":{"min":1,"max":314},"fee":{"feeType":"Fixed","min":0.5,"max":314},"infoUrl":"","paymentScheme":"PROP"}}]}