{"id":"neetcoin","description":"\"NEET\" is an acronym \"Not in Education, Employment or Training\" and refers to those who are not involved in school, occupation, or vocational training.","links":[{"type":"Website","url":"https://neetcoin.jp/en/"},{"type":"Explorer","url":"http://exp.neetcoin.jp:3001/"},{"type":"Explorer","url":"https://twitter.com/neetcoin_jp"},{"type":"Explorer","url":"https://bitcointalk.org/index.php?topic=2663136.0"},{"type":"Explorer","url":"https://github.com/NEETCOINTeam"}],"name":"NeetCoin","abbreviation":"NEET","algorithm":{"id":"scrypt","name":"Scrypt"},"pools":[{"name":"CoinStop.me","url":"https://coinstop.me","serverLocation":["US"],"paymentInformation":{"paymentScheme":"PROP","paymentThreshold":0.025,"paymentCurrency":"BTC","fee":0.5}},{"name":"StrayaPool.com","url":"http://strayapool.com","serverLocation":["AU"],"paymentInformation":{"paymentScheme":"PROP","paymentThreshold":0.1,"fee":1}},{"name":"BlockMasters.co","url":"http://blockmasters.co","serverLocation":["US","EU"],"paymentInformation":{"paymentScheme":"PROP","paymentThreshold":0.0025,"fee":0.25}},{"name":"MiningPoolRw.de","url":"https://pool.miningpoolrw.de","serverLocation":["DE"],"paymentInformation":{"paymentScheme":"PROP","paymentThreshold":0.01,"fee":1.1}},{"name":"CoinCave.nl","url":"https://coincave.nl","serverLocation":["NL"],"paymentInformation":{"paymentScheme":"PROP","paymentThreshold":1,"fee":1.5}},{"name":"ZPool","url":"https://zpool.ca","serverLocation":["US","EU","ASIA"],"paymentInformation":{"paymentScheme":"PROP","paymentThreshold":0.05,"fee":0.75}},{"name":"ZergPool","url":"http://zergpool.com","serverLocation":["US"],"paymentInformation":{"paymentScheme":"PROP","paymentThreshold":0.0001,"paymentCurrency":"BTC","fee":0.5}}],"wallets":[]}