{"id":"note-blockchain","description":"Note is a cryptocurrency that is designed to be fun and easy to use. The mobile wallet does not require a complicated and unrecoverable backup such as 24 word phrases or private key.","links":[{"name":"Website","platform":"website","url":"https://www.notebc.com/"},{"name":"Explorer","platform":"explorer","url":"http://explorer.notebc.io/"},{"name":"Twitter","platform":"twitter","url":"https://twitter.com/BlockchainNote"},{"name":"Discord","platform":"discord","url":"https://discord.gg/auhWAvR"},{"name":"BitcoinTalk","platform":"bitcointalk","url":"https://bitcointalk.org/index.php?topic=5097914.0"}],"name":"Note Blockchain","abbreviation":"NTBC","algorithm":{"id":"scrypt","name":"Scrypt"},"pools":[{"name":"CoinMiningPool.org","url":"https://coinminingpool.org","serverLocation":["US","EU"],"paymentInformation":{"paymentThreshold":{"min":0.001,"max":314},"fee":{"feeType":"Fixed","min":0.8,"max":314},"infoUrl":"","paymentScheme":"PROP","paymentInterval":3600}},{"name":"NoteBC.space","url":"https://mining.notebc.space","serverLocation":["FR"],"paymentInformation":{"paymentThreshold":{"min":100,"max":314},"fee":{"feeType":"Fixed","min":1,"max":314},"infoUrl":"","paymentScheme":"PROP","paymentInterval":7200}},{"name":"BPool.id","url":"https://bpool.id","serverLocation":["SG"],"paymentInformation":{"paymentThreshold":{"min":0.001,"max":314},"fee":{"feeType":"Fixed","min":1,"max":314},"infoUrl":"","paymentScheme":"PROP","paymentInterval":7200}},{"name":"Mpos-Pools.com","url":"https://s2.mpos-pools.com/notes","serverLocation":["FR"],"paymentInformation":{"paymentThreshold":{"min":1,"max":314},"fee":{"feeType":"Fixed","min":0.25,"max":314},"infoUrl":"","paymentScheme":"PROP"}},{"name":"CoinCave.nl","url":"https://coincave.nl","serverLocation":["NL"],"paymentInformation":{"paymentThreshold":{"min":1,"max":314},"fee":{"feeType":"Fixed","min":1.5,"max":314},"infoUrl":"","paymentScheme":"PROP","paymentInterval":7200}},{"name":"NewPool.eu","url":"http://www.newpool.eu/pool","serverLocation":["NL"],"paymentInformation":{"paymentThreshold":{"min":1,"max":314},"fee":{"feeType":"Fixed","min":1,"max":314},"infoUrl":"","paymentScheme":"PROP","paymentInterval":3600}},{"name":"Bitcoin-Rebooted.xyz","url":"http://pool.bitcoin-rebooted.xyz","serverLocation":["US"],"paymentInformation":{"paymentThreshold":{"min":0.001,"max":314},"fee":{"feeType":"Fixed","min":0.75,"max":314},"infoUrl":"","paymentScheme":"PROP"}},{"name":"CryptoCrop.net","url":"https://farm.cryptocrop.net","serverLocation":["US"],"paymentInformation":{"infoUrl":"","paymentThreshold":{"min":0.001,"max":314},"paymentScheme":"PROP","fee":{"feeType":"Fixed","min":0,"max":314},"paymentInterval":7200}}]}