{"id":"pegascoin","description":"Decentralized Cryptocurrency - Platform For P2P Transactions","links":[{"type":"Website","url":"http://pegascoin.com/"},{"type":"Explorer","url":"http://explorer.pegascoin.com/"},{"type":"Explorer","url":"https://www.facebook.com/1489614771136573"},{"type":"Explorer","url":"https://twitter.com/Pegascoin"},{"type":"Explorer","url":"https://bitcointalk.org/index.php?topic=2132259.0"},{"type":"Explorer","url":"https://github.com/Pegascoin"}],"name":"Pegascoin","abbreviation":"PGC","algorithm":{"id":"ethash","name":"Ethash"},"pools":[{"name":"FairPool.xyz","url":"https://pgc.fairpool.xyz","serverLocation":["US"],"paymentInformation":{"paymentScheme":"PPLNS","paymentThreshold":1,"fee":1}},{"name":"Comining.io","url":"http://comining.io/?ref=AFx9pURxsWfsqiVXF5s5f8g","serverLocation":["US","EU","RU","ASIA"],"paymentInformation":{"paymentScheme":"PPLNT","paymentThreshold":5,"fee":1}},{"name":"Comining.io","url":"http://comining.io/?ref=AFx9pURxsWfsqiVXF5s5f8g","serverLocation":["US","EU","RU","ASIA"],"paymentInformation":{"paymentScheme":"SOLO","paymentThreshold":5,"fee":1}},{"name":"Comining.io","url":"http://comining.io/?ref=AFx9pURxsWfsqiVXF5s5f8g","serverLocation":["US","EU","RU","ASIA"],"paymentInformation":{"paymentScheme":"PROP","paymentThreshold":5,"fee":1}},{"name":"MinerPool.net","url":"http://pgc.minerpool.net","serverLocation":["US","EU","AU","ASIA"],"paymentInformation":{"paymentScheme":"PPSW","paymentThreshold":1,"fee":1}}],"wallets":[]}