{"name":"Conceal","abbreviation":"CCX","slug":"conceal","description":"Conceal.Network is a decentralized blockchain bank, with deposits and investments paying interest rates, without involvement of financial institutions, powered by 100% open source code.","lastUpdated":"2019-08-05T17:59:00.489Z","subPools":[{"paymentInformation":{"paymentThreshold":{"min":3,"max":314},"fee":{"feeType":"Fixed","min":0.9,"max":314},"infoUrl":"","paymentScheme":"PROP"},"isAlive":false,"lastUpdated":"2019-08-06T15:34:51.162Z","url":"http://ccx.aiwakuang.cn","slug":"2794","poolProfile":{"isVerified":false,"name":"Aiwakuang.cn","slug":"aiwakuang-cn"}},{"paymentInformation":{"paymentThreshold":{"min":3,"max":314},"fee":{"feeType":"Fixed","min":1,"max":314},"infoUrl":"","paymentScheme":"PPLNS"},"isAlive":true,"lastUpdated":"2019-08-06T15:34:51.162Z","url":"https://ccx.romining.farm","slug":"2795","poolProfile":{"isVerified":false,"name":"Romining.farm","slug":"romining-farm"}},{"paymentInformation":{"paymentThreshold":{"min":3,"max":314},"fee":{"feeType":"Fixed","min":1,"max":314},"infoUrl":"","paymentScheme":"SOLO"},"isAlive":false,"lastUpdated":"2019-08-06T15:34:51.162Z","url":"https://ccx.romining.farm","slug":"2796","poolProfile":{"isVerified":false,"name":"Romining.farm","slug":"romining-farm"}},{"paymentInformation":{"paymentThreshold":{"min":3,"max":314},"fee":{"feeType":"Fixed","min":0.9,"max":314},"infoUrl":"","paymentScheme":"PROP"},"isAlive":true,"lastUpdated":"2019-08-06T15:34:51.162Z","url":"https://conceal.herominers.com","slug":"2797","poolProfile":{"isVerified":false,"name":"HeroMiners.com","slug":"herominers-com"}},{"paymentInformation":{"paymentThreshold":{"min":3,"max":314},"fee":{"feeType":"Fixed","min":0.9,"max":314},"infoUrl":"","paymentScheme":"SOLO"},"isAlive":true,"lastUpdated":"2019-08-06T15:34:51.162Z","url":"https://conceal.herominers.com","slug":"2798","poolProfile":{"isVerified":false,"name":"HeroMiners.com","slug":"herominers-com"}},{"paymentInformation":{"paymentThreshold":{"min":1,"max":314},"fee":{"feeType":"Fixed","min":0.9,"max":314},"infoUrl":"","paymentScheme":"PROP"},"isAlive":true,"lastUpdated":"2019-08-06T15:34:51.162Z","url":"https://conceal.luckypool.io","slug":"2799","poolProfile":{"isVerified":false,"name":"LuckyPool.io","slug":"luckypool-io"}},{"paymentInformation":{"paymentThreshold":{"min":10,"max":314},"fee":{"feeType":"Fixed","min":0.5,"max":314},"infoUrl":"","paymentScheme":"PPLNS"},"isAlive":true,"lastUpdated":"2019-08-06T15:34:51.162Z","url":"https://ccx.go-mine.it","slug":"2802","poolProfile":{"isVerified":false,"name":"Go-Mine.it","slug":"go-mine-it"}},{"paymentInformation":{"paymentThreshold":{"min":10,"max":314},"fee":{"feeType":"Fixed","min":0.5,"max":314},"infoUrl":"","paymentScheme":"SOLO"},"isAlive":true,"lastUpdated":"2019-08-06T15:34:51.162Z","url":"https://ccx.go-mine.it","slug":"2803","poolProfile":{"isVerified":false,"name":"Go-Mine.it","slug":"go-mine-it"}},{"paymentInformation":{"paymentThreshold":{"min":1,"max":314},"fee":{"feeType":"Fixed","min":0,"max":314},"infoUrl":"","paymentScheme":"PPLNS"},"isAlive":true,"lastUpdated":"2019-08-06T15:34:51.162Z","url":"https://webccx.semipool.com","slug":"2805","poolProfile":{"isVerified":false,"name":"SemiPool.com","slug":"semipool-com"}},{"paymentInformation":{"paymentThreshold":{"min":1,"max":314},"fee":{"feeType":"Fixed","min":0.8,"max":314},"infoUrl":"","paymentScheme":"PROP"},"isAlive":true,"lastUpdated":"2019-08-06T15:34:51.162Z","url":"https://ccx.codpool.com","slug":"2806","poolProfile":{"isVerified":false,"name":"CodPool.com","slug":"codpool-com"}},{"paymentInformation":{"paymentThreshold":{"min":1,"max":314},"fee":{"feeType":"Fixed","min":0.9,"max":314},"infoUrl":"https://spacepools.org/#!/startMining/CCX","paymentScheme":"PPLNS","paymentInterval":10800},"isAlive":true,"lastUpdated":"2019-08-09T08:01:22.944Z","url":"https://spacepools.org/#!/startMining/CCX","slug":"6340","poolProfile":{"isVerified":false,"name":"SpacePools.org","slug":"spacepools-org"}},{"paymentInformation":{"paymentThreshold":{"min":1,"max":314},"fee":{"feeType":"Fixed","min":0.4,"max":314},"infoUrl":"https://ccx.scecf.org/","paymentScheme":"PROP","paymentInterval":3600},"isAlive":true,"lastUpdated":"2019-08-09T08:01:22.944Z","url":"https://ccx.scecf.org/","slug":"6400","poolProfile":{"isVerified":false,"name":"Scecf.org","slug":"scecf-org"}},{"paymentInformation":{"infoUrl":"https://pool.conceal.network/#faq","paymentThreshold":{"min":3,"max":314},"paymentScheme":"PROP","fee":{"feeType":"Fixed","min":1,"max":314},"paymentInterval":30},"isAlive":true,"lastUpdated":"2019-08-09T19:48:16.725Z","url":"https://pool.conceal.network","slug":"2792","poolProfile":{"isVerified":false,"name":"Conceal.network","slug":"conceal-network"}},{"paymentInformation":{"infoUrl":"https://conceal.my-mining-pool.de/","paymentThreshold":{"min":3,"max":314},"paymentScheme":"PROP","fee":{"feeType":"Fixed","min":0,"max":314},"paymentInterval":1800},"isAlive":true,"lastUpdated":"2019-08-12T09:08:17.016Z","url":"https://conceal.my-mining-pool.de","slug":"2800","poolProfile":{"isVerified":false,"name":"My-Mining-Pool.de","slug":"my-mining-pool-de"}},{"paymentInformation":{"infoUrl":"https://conceal.modpool.org/","paymentThreshold":{"min":3,"max":314},"paymentScheme":"PROP","fee":{"feeType":"Fixed","min":0,"max":314},"paymentInterval":300},"isAlive":true,"lastUpdated":"2019-08-12T12:32:15.477Z","url":"https://conceal.modpool.org","slug":"2804","poolProfile":{"isVerified":false,"name":"ModPool.org","slug":"modpool-org"}},{"paymentInformation":{"infoUrl":"https://conceal.blockfoundry.org","paymentThreshold":{"min":3,"max":314},"paymentScheme":"PROP","fee":{"feeType":"Fixed","min":0.5,"max":314},"paymentInterval":3600},"isAlive":true,"lastUpdated":"2019-08-12T12:51:27.714Z","url":"https://conceal.blockfoundry.org","slug":"2801","poolProfile":{"isVerified":false,"name":"BlockFoundry.org","slug":"blockfoundry-org"}},{"paymentInformation":{"infoUrl":"https://ccx.bluerockpools.net/","paymentThreshold":{"min":3,"max":314},"paymentScheme":"PROP","fee":{"feeType":"Fixed","min":0,"max":314},"paymentInterval":300},"isAlive":true,"lastUpdated":"2019-08-12T13:09:38.753Z","url":"https://ccx.bluerockpools.net","slug":"2793","poolProfile":{"isVerified":false,"name":"BlueRockPools","slug":"bluerockpools"}},{"paymentInformation":{"infoUrl":"https://ccx.solopool.org/","paymentThreshold":{"min":1,"max":314},"paymentScheme":"SOLO","fee":{"feeType":"Fixed","min":1,"max":314},"paymentInterval":3600},"isAlive":true,"lastUpdated":"2019-08-22T08:20:21.526Z","url":"https://ccx.solopool.org/","slug":"6838","poolProfile":{"isVerified":false,"name":"SoloPool.org","slug":"solopool-org"}}],"numberOfSubPools":18,"links":[{"name":"Website","platform":"website","url":"https://conceal.network/"},{"name":"Explorer","platform":"explorer","url":"https://explorer.conceal.network/"},{"name":"Twitter","platform":"twitter","url":"https://twitter.com/ConcealNetwork"},{"name":"Reddit","platform":"reddit","url":"https://www.reddit.com/r/ConcealNetwork/"},{"name":"Medium","platform":"medium","url":"https://medium.com/@ConcealNetwork"},{"name":"Discord","platform":"discord","url":"http://discord.conceal.network/"},{"name":"Telegram","platform":"telegram","url":"https://t.co/55klBHKGUR"},{"name":"BitcoinTalk","platform":"bitcointalk","url":"https://bitcointalk.org/index.php?topic=5086106"},{"name":"GitHub","platform":"github","url":"https://github.com/ConcealNetwork"}],"algorithm":{"name":"CryptoNight Conceal","type":"CRYPTONIGHT_CONCEAL_ALGORITHM","slug":"cryptonight-conceal"},"coinCap":{"isAvailable":false,"id":"noid"}}