{"name":"Metaverse","abbreviation":"ETP","slug":"metaverse","description":"Metaverse is an open-source public blockchain that provides digital assets, digital identities and Oracles as a foundational infrastructure for social and enterprise needs. Through Blockchain-as-a-Service (BaaS), we make convenient, secure digital financial services accessible to all applications at virtually no cost.","lastUpdated":"2019-08-05T17:59:00.489Z","subPools":[{"paymentInformation":{"paymentThreshold":{"min":1,"max":314},"fee":{"feeType":"Fixed","min":0.5,"max":314},"infoUrl":"","paymentScheme":"PROP","paymentInterval":7200},"isAlive":true,"lastUpdated":"2019-08-06T15:34:51.162Z","url":"http://etp.dodopool.com","slug":"746","poolProfile":{"isVerified":false,"name":"DodoPool.com","slug":"dodopool-com"}},{"paymentInformation":{"paymentThreshold":{"min":0.5,"max":314},"fee":{"feeType":"Fixed","min":0.25,"max":314},"infoUrl":"","paymentScheme":"PROP","paymentInterval":7200},"isAlive":true,"lastUpdated":"2019-08-06T15:34:51.162Z","url":"http://etp.sandpool.org","slug":"747","poolProfile":{"isVerified":false,"name":"SandPool.org","slug":"sandpool-org"}},{"paymentInformation":{"paymentThreshold":{"min":1,"max":314},"fee":{"feeType":"Fixed","min":0.5,"max":314},"infoUrl":"","paymentScheme":"PPLNS"},"isAlive":true,"lastUpdated":"2019-08-06T15:34:51.162Z","url":"https://ethashpool.com/etp","slug":"748","poolProfile":{"isVerified":false,"name":"EthashPool.com","slug":"ethashpool-com"}},{"paymentInformation":{"paymentThreshold":{"min":0.5,"max":314},"fee":{"feeType":"Fixed","min":1,"max":314},"infoUrl":"","paymentScheme":"PPLNS","paymentInterval":3600},"isAlive":true,"lastUpdated":"2019-08-06T15:34:51.162Z","url":"https://etp.saturnpool.com","slug":"749","poolProfile":{"isVerified":false,"name":"SaturnPool.com","slug":"saturnpool-com"}},{"paymentInformation":{"paymentThreshold":{"min":0.51,"max":314},"fee":{"feeType":"Fixed","min":0.5,"max":314},"infoUrl":"","paymentScheme":"PPLNS"},"isAlive":true,"lastUpdated":"2019-08-06T15:34:51.162Z","url":"http://pool.baikalmine.com/en/etp","slug":"752","poolProfile":{"isVerified":false,"name":"BaikalMine.com","slug":"baikalmine-com"}},{"paymentInformation":{"paymentThreshold":{"min":0.51,"max":314},"fee":{"feeType":"Fixed","min":1,"max":314},"infoUrl":"","paymentScheme":"SOLO"},"isAlive":true,"lastUpdated":"2019-08-06T15:34:51.162Z","url":"http://pool.baikalmine.com/en/etp-solo","slug":"753","poolProfile":{"isVerified":false,"name":"BaikalMine.com","slug":"baikalmine-com"}},{"paymentInformation":{"paymentThreshold":{"min":1,"max":314},"fee":{"feeType":"Fixed","min":1,"max":314},"infoUrl":"","paymentScheme":"FPPS"},"isAlive":true,"lastUpdated":"2019-08-06T15:34:51.162Z","url":"https://www.dpool.top","slug":"754","poolProfile":{"isVerified":false,"name":"DPool.top","slug":"dpool-top"}},{"paymentInformation":{"paymentThreshold":{"min":0.1,"max":314},"fee":{"feeType":"Fixed","min":0.5,"max":314},"infoUrl":"","paymentScheme":"PROP"},"isAlive":true,"lastUpdated":"2019-08-06T15:34:51.162Z","url":"https://etp.topmining.co.kr","slug":"757","poolProfile":{"isVerified":false,"name":"TopMining.co.kr","slug":"topmining-co-kr"}},{"paymentInformation":{"paymentThreshold":{"min":314,"max":314},"fee":{"feeType":"Fixed","min":1,"max":314},"infoUrl":"","paymentScheme":"SOLO"},"isAlive":true,"lastUpdated":"2019-08-06T15:34:51.162Z","url":"https://etps.mole-pool.net","slug":"758","poolProfile":{"isVerified":false,"name":"Mole-Pool.net","slug":"mole-pool-net"}},{"paymentInformation":{"paymentThreshold":{"min":0.5,"max":314},"fee":{"feeType":"Fixed","min":1,"max":314},"infoUrl":"","paymentScheme":"PPLNS","paymentInterval":1200},"isAlive":true,"lastUpdated":"2019-08-06T15:34:51.162Z","url":"http://etp.altpool.pro","slug":"759","poolProfile":{"isVerified":false,"name":"AltPool.pro","slug":"altpool-pro"}},{"paymentInformation":{"paymentThreshold":{"min":0.5,"max":314},"fee":{"feeType":"Fixed","min":1,"max":314},"infoUrl":"","paymentScheme":"SOLO","paymentInterval":1200},"isAlive":true,"lastUpdated":"2019-08-06T15:34:51.162Z","url":"http://solo-etp.altpool.pro","slug":"760","poolProfile":{"isVerified":false,"name":"AltPool.pro","slug":"altpool-pro"}},{"paymentInformation":{"paymentThreshold":{"min":0.1,"max":314},"fee":{"feeType":"Fixed","min":1,"max":314},"infoUrl":"","paymentScheme":"PPLNS","paymentInterval":0},"isAlive":true,"lastUpdated":"2019-08-06T15:34:51.162Z","url":"https://etp.fairpool.xyz","slug":"761","poolProfile":{"isVerified":false,"name":"FairPool.xyz","slug":"fairpool-xyz"}},{"paymentInformation":{"paymentThreshold":{"min":0.5,"max":314},"fee":{"feeType":"Fixed","min":1,"max":314},"infoUrl":"","paymentScheme":"SOLO"},"isAlive":true,"lastUpdated":"2019-08-06T15:34:51.162Z","url":"http://etp.farmine.net","slug":"765","poolProfile":{"isVerified":false,"name":"FarMine.net","slug":"farmine-net"}},{"paymentInformation":{"paymentThreshold":{"min":1,"max":314},"fee":{"feeType":"Fixed","min":1,"max":314},"infoUrl":"","paymentScheme":"PPS"},"isAlive":true,"lastUpdated":"2019-08-06T15:34:51.162Z","url":"https://xzrm.com/pool?coin=etp","slug":"766","poolProfile":{"isVerified":false,"name":"Xzrm.com","slug":"xzrm-com"}},{"paymentInformation":{"infoUrl":"http://comining.io","paymentThreshold":{"min":0.5,"max":1000},"paymentScheme":"SOLO","fee":{"feeType":"Fixed","min":1,"max":314},"paymentInterval":0},"isAlive":true,"lastUpdated":"2019-08-06T19:10:09.786Z","url":"http://comining.io/?ref=AFx9pURxsWfsqiVXF5s5f8g","slug":"763","poolProfile":{"isVerified":true,"name":"Comining.io","slug":"comining-io"}},{"paymentInformation":{"infoUrl":"http://comining.io","paymentThreshold":{"min":0.5,"max":1000},"paymentScheme":"PROP","fee":{"feeType":"Fixed","min":1,"max":314},"paymentInterval":0},"isAlive":true,"lastUpdated":"2019-08-06T19:10:21.431Z","url":"http://comining.io/?ref=AFx9pURxsWfsqiVXF5s5f8g","slug":"764","poolProfile":{"isVerified":true,"name":"Comining.io","slug":"comining-io"}},{"paymentInformation":{"infoUrl":"http://comining.io","paymentThreshold":{"min":0.5,"max":1000},"paymentScheme":"PPLNT","fee":{"feeType":"Fixed","min":1,"max":314},"paymentInterval":0},"isAlive":true,"lastUpdated":"2019-08-07T08:13:21.570Z","url":"http://comining.io/?ref=AFx9pURxsWfsqiVXF5s5f8g","slug":"762","poolProfile":{"isVerified":true,"name":"Comining.io","slug":"comining-io"}},{"paymentInformation":{"infoUrl":"https://www.myminers.org/faq.html","paymentThreshold":{"min":0.1,"max":314},"paymentScheme":"SOLO","fee":{"feeType":"Fixed","min":0.1,"max":314},"paymentInterval":0},"isAlive":true,"lastUpdated":"2019-08-07T08:24:11.186Z","url":"https://solo-etp.myminers.org","slug":"751","poolProfile":{"isVerified":false,"name":"MyMiners.org","slug":"myminers-org"}},{"paymentInformation":{"infoUrl":"https://etp.europool.me","paymentThreshold":{"min":0.1,"max":314},"paymentScheme":"PPLNS","fee":{"feeType":"Fixed","min":0.4,"max":314},"paymentInterval":0},"isAlive":true,"lastUpdated":"2019-08-08T07:52:06.585Z","url":"https://etp.europool.me","slug":"750","poolProfile":{"isVerified":false,"name":"EuroPool.me","slug":"europool-me"}},{"paymentInformation":{"infoUrl":"https://solo-etp.2miners.com","paymentThreshold":{"min":1,"max":314},"paymentScheme":"SOLO","fee":{"feeType":"Fixed","min":1.5,"max":314},"paymentInterval":7200},"isAlive":true,"lastUpdated":"2019-08-21T10:02:04.277Z","url":"https://solo-etp.2miners.com","slug":"756","poolProfile":{"isVerified":false,"name":"2Miners.com","slug":"2miners-com"}},{"paymentInformation":{"infoUrl":"https://etp.2miners.com","paymentThreshold":{"min":0.5,"max":314},"paymentScheme":"PPLNS","fee":{"feeType":"Fixed","min":1,"max":314},"paymentInterval":7200},"isAlive":true,"lastUpdated":"2019-08-21T10:02:07.539Z","url":"https://etp.2miners.com","slug":"755","poolProfile":{"isVerified":false,"name":"2Miners.com","slug":"2miners-com"}},{"paymentInformation":{"infoUrl":"https://www.f2pool.com","paymentThreshold":{"min":5,"max":314},"paymentScheme":"PPS","fee":{"feeType":"Fixed","min":3,"max":314},"paymentInterval":86400},"isAlive":true,"lastUpdated":"2019-08-22T06:23:06.218Z","url":"https://www.f2pool.com","slug":"767","poolProfile":{"isVerified":false,"name":"F2Pool","slug":"f2pool"}}],"numberOfSubPools":22,"links":[{"name":"Website","platform":"website","url":"https://mvs.org/"},{"name":"Explorer","platform":"explorer","url":"https://Explorer.mvs.org/"},{"name":"Announcement","platform":"announcement","url":"https://bitcointalk.org/index.php?topic=2134505"},{"name":"Discord","platform":"discord","url":"https://discord.gg/ubgMRts"},{"name":"Reddit","platform":"reddit","url":"https://reddit.com/r/Metaverse_Blockchain"},{"name":"Twitter","platform":"twitter","url":"https://twitter.com/mvs_org "},{"name":"GitHub","platform":"github","url":"https://github.com/mvs-org"}],"algorithm":{"name":"Ethash","type":"ETHASH_ALGORITHM","slug":"ethash"},"coinCap":{"isAvailable":true,"id":"metaverse"}}