{"name":"Aussie-Pools.com","slug":"aussie-pools-com","website":"https://aussie-pools.com/","description":"The leading pools of Australia, all waiting for your hash!","isVerified":false,"lastUpdated":"2019-08-06T14:45:54.821Z","subPools":[{"paymentInformation":{"paymentThreshold":{"min":1,"max":314},"fee":{"feeType":"Fixed","min":0.5,"max":314},"infoUrl":"","paymentScheme":"PROP"},"isAlive":true,"lastUpdated":"2019-08-06T15:34:51.162Z","url":"https://loki.aussie-pools.com","slug":"1421","coin":{"name":"Loki","abbreviation":"LOKI","slug":"loki","algorithm":{"name":"Random XL","slug":"random-xl"}}},{"paymentInformation":{"paymentThreshold":{"min":10,"max":314},"fee":{"feeType":"Fixed","min":0.3,"max":314},"infoUrl":"","paymentScheme":"PROP"},"isAlive":true,"lastUpdated":"2019-08-06T15:34:51.162Z","url":"https://graft.aussie-pools.com","slug":"1650","coin":{"name":"Graft","abbreviation":"GRFT","slug":"graft","algorithm":{"name":"CryptoNight V8","slug":"cryptonight-v8"}}}],"numberOfSubPools":2,"links":[{"name":"Discord","platform":"discord","url":"https://discord.gg/JCus5Xv"},{"name":"Contact","platform":"contact","url":"admin@aussie-pools.com"}]}