{"name":"LycheeBit.com","slug":"lycheebit-com","website":"https://www.lycheebit.com/","description":"","isVerified":false,"lastUpdated":"2019-08-06T14:45:54.821Z","subPools":[{"paymentInformation":{"paymentThreshold":{"min":0.1,"max":314},"fee":{"feeType":"Fixed","min":1,"max":314},"infoUrl":"","paymentScheme":"","paymentInterval":3600},"isAlive":true,"lastUpdated":"2019-08-06T15:34:51.162Z","url":"https://www.lycheebit.com","slug":"2566","coin":{"name":"PlatinumBAR","abbreviation":"XPTX","slug":"platinumbar","algorithm":{"name":"Quark","slug":"quark"}}},{"paymentInformation":{"paymentThreshold":{"min":0.1,"max":314},"fee":{"feeType":"Fixed","min":1,"max":314},"infoUrl":"","paymentScheme":"","paymentInterval":3600},"isAlive":false,"lastUpdated":"2019-08-06T15:34:51.162Z","url":"https://www.lycheebit.com","slug":"3618","coin":{"name":"VirtacoinPlus","abbreviation":"XVP","slug":"virtacoinplus","algorithm":{"name":"X11","slug":"x11"}}},{"paymentInformation":{"paymentThreshold":{"min":0.1,"max":314},"fee":{"feeType":"Fixed","min":1,"max":314},"infoUrl":"","paymentScheme":"","paymentInterval":3600},"isAlive":true,"lastUpdated":"2019-08-06T15:34:51.162Z","url":"https://www.lycheebit.com","slug":"3657","coin":{"name":"Arepacoin","abbreviation":"AREPA","slug":"arepacoin","algorithm":{"name":"Scrypt","slug":"scrypt"}}},{"paymentInformation":{"paymentThreshold":{"min":0.1,"max":314},"fee":{"feeType":"Fixed","min":1,"max":314},"infoUrl":"","paymentScheme":"","paymentInterval":3600},"isAlive":true,"lastUpdated":"2019-08-06T15:34:51.162Z","url":"https://www.lycheebit.com","slug":"4813","coin":{"name":"RACEcoin","abbreviation":"RACE","slug":"racecoin","algorithm":{"name":"Lyra2REv2","slug":"lyra2rev2"}}},{"paymentInformation":{"paymentThreshold":{"min":0.1,"max":314},"fee":{"feeType":"Fixed","min":1,"max":314},"infoUrl":"","paymentScheme":"","paymentInterval":3600},"isAlive":true,"lastUpdated":"2019-08-06T15:34:51.162Z","url":"https://www.lycheebit.com","slug":"5118","coin":{"name":"Bithold","abbreviation":"BHD","slug":"bithold","algorithm":{"name":"C11","slug":"c11"}}},{"paymentInformation":{"paymentThreshold":{"min":0.1,"max":314},"fee":{"feeType":"Fixed","min":1,"max":314},"infoUrl":"https://www.lycheebit.com/","paymentScheme":"PROP","paymentInterval":3600},"isAlive":true,"lastUpdated":"2019-08-08T06:01:30.779Z","url":"https://www.lycheebit.com/","slug":"6058","coin":{"name":"Bithold","abbreviation":"BHD","slug":"bithold","algorithm":{"name":"C11","slug":"c11"}}}],"numberOfSubPools":6,"links":[{"name":"BitcoinTalk","platform":"bitcointalk","url":"https://bitcointalk.org/index.php?action=profile;u=1162211"}]}