{"name":"MatPool.io","slug":"matpool-io","website":"https://matpool.io/","description":"","isVerified":false,"lastUpdated":"2019-08-06T14:45:54.821Z","subPools":[{"paymentInformation":{"paymentThreshold":{"min":10,"max":314},"fee":{"feeType":"Fixed","min":3,"max":314},"infoUrl":"","paymentScheme":"PPS"},"isAlive":true,"lastUpdated":"2019-08-06T15:34:51.162Z","url":"http://matpool.io","slug":"556","coin":{"name":"Bytom","abbreviation":"BTM","slug":"bytom","algorithm":{"name":"Tensority","slug":"tensority"}}},{"paymentInformation":{"paymentThreshold":{"min":1,"max":314},"fee":{"feeType":"Fixed","min":3,"max":314},"infoUrl":"","paymentScheme":"PPS"},"isAlive":true,"lastUpdated":"2019-08-06T15:34:51.162Z","url":"http://matpool.io","slug":"1043","coin":{"name":"Horizen","abbreviation":"ZEN","slug":"horizen","algorithm":{"name":"Equihash","slug":"equihash"}}},{"paymentInformation":{"paymentThreshold":{"min":0.1,"max":314},"fee":{"feeType":"Fixed","min":3,"max":314},"infoUrl":"https://matpool.io/","paymentScheme":"PPS","paymentInterval":0},"isAlive":true,"lastUpdated":"2019-08-09T08:01:22.944Z","url":"https://matpool.io/","slug":"6376","coin":{"name":"Zcash","abbreviation":"ZEC","slug":"zcash","algorithm":{"name":"Equihash","slug":"equihash"}}},{"paymentInformation":{"paymentThreshold":{"min":0.1,"max":314},"fee":{"feeType":"Fixed","min":3,"max":314},"infoUrl":"https://matpool.io/","paymentScheme":"PPS","paymentInterval":0},"isAlive":true,"lastUpdated":"2019-08-09T08:01:22.944Z","url":"https://matpool.io/","slug":"6377","coin":{"name":"Ethereum Classic","abbreviation":"ETC","slug":"ethereum-classic","algorithm":{"name":"Ethash","slug":"ethash"}}}],"numberOfSubPools":4,"links":[{"name":"Contact","platform":"contact","url":"support@matpool.io"}]}