{"name":"MiningFrance.io","slug":"miningfrance-io","website":"https://b2g.miningfrance.io/","description":"","isVerified":false,"lastUpdated":"2019-08-06T14:45:54.821Z","subPools":[{"paymentInformation":{"paymentThreshold":{"min":1,"max":314},"fee":{"feeType":"Fixed","min":1,"max":314},"infoUrl":"","paymentScheme":"PROP","paymentInterval":43200},"isAlive":true,"lastUpdated":"2019-08-06T15:34:51.162Z","url":"https://b2g.miningfrance.io","slug":"4842","coin":{"name":"Bitcoiin","abbreviation":"B2G","slug":"bitcoiin","algorithm":{"name":"Ethash","slug":"ethash"}}}],"numberOfSubPools":1,"links":[]}