{"name":"MultiMiner.us","slug":"multiminer-us","website":"https://arq.multiminer.us/","description":"","isVerified":false,"lastUpdated":"2019-08-06T14:45:54.821Z","subPools":[{"paymentInformation":{"paymentThreshold":{"min":1,"max":314},"fee":{"feeType":"Fixed","min":0.5,"max":314},"infoUrl":"","paymentScheme":"PROP"},"isAlive":true,"lastUpdated":"2019-08-06T15:34:51.162Z","url":"https://mutex.multiminer.us","slug":"2418","coin":{"name":"Mutex","abbreviation":"MUTX","slug":"mutex","algorithm":{"name":"CryptoNight V7","slug":"cryptonight-v7"}}},{"paymentInformation":{"paymentThreshold":{"min":0.1,"max":314},"fee":{"feeType":"Fixed","min":0.5,"max":314},"infoUrl":"","paymentScheme":"PROP"},"isAlive":true,"lastUpdated":"2019-08-06T15:34:51.162Z","url":"https://arq.multiminer.us","slug":"3197","coin":{"name":"ArQmA","abbreviation":"ARQ","slug":"arqma","algorithm":{"name":"CryptoNight Turtle","slug":"cryptonight-turtle"}}},{"paymentInformation":{"paymentThreshold":{"min":314,"max":314},"fee":{"feeType":"Fixed","min":314,"max":314},"infoUrl":"","paymentScheme":""},"isAlive":false,"lastUpdated":"2019-08-06T15:34:51.162Z","url":"https://cpa.multiminer.us","slug":"3339","coin":{"name":"CryptoPayAfrica","abbreviation":"CPA","slug":"cryptopayafrica","algorithm":{"name":"CryptoNight V7","slug":"cryptonight-v7"}}}],"numberOfSubPools":3,"links":[{"name":"Discord","platform":"discord","url":"https://discord.gg/tYpbxXX"}]}